[
  {
    "id": "item_001",
    "name": "NB 1906L",
    "brand": "New Balance",
    "imagePath": "https://raw.githubusercontent.com/MoonRProjet/my-dressing-assets/main/shop/chaussures/NB-1906L-Photoroom.png",
    "mainCategory": "Chaussures",
    "subCategory": "Baskets",
    "price": 160,
    "isSponsor": false
  },
  {
    "id": "item_1779169613093",
    "name": "Jean Baggy",
    "brand": "Zara",
    "imagePath": "https://raw.githubusercontent.com/MoonRProjet/my-dressing-assets/main/shop/bas/img_1779169609894.png",
    "mainCategory": "Bas",
    "subCategory": "Jean",
    "price": 39.99,
    "isSponsor": false
  },
  {
    "id": "item_1779169754508",
    "name": "Veste Japan Style Marron Délavé",
    "brand": "That's Life",
    "imagePath": "https://raw.githubusercontent.com/MoonRProjet/my-dressing-assets/main/shop/hauts/img_1779169751671.png",
    "mainCategory": "Haut",
    "subCategory": "Gilet",
    "price": 90.0,
    "isSponsor": false
  },
  {
    "id": "item_1779169835809",
    "name": "Jean Baggy Denim",
    "brand": "That's Life",
    "imagePath": "https://raw.githubusercontent.com/MoonRProjet/my-dressing-assets/main/shop/bas/img_1779169833020.png",
    "mainCategory": "Bas",
    "subCategory": "Jean",
    "price": 52.95,
    "isSponsor": false
  },
  {
    "id": "item_1779170094309",
    "name": "Veste Japan Style Délavé Noir",
    "brand": "That's Life",
    "imagePath": "https://raw.githubusercontent.com/MoonRProjet/my-dressing-assets/main/shop/hauts/img_1779170091624.png",
    "mainCategory": "Haut",
    "subCategory": "Gilet",
    "price": 90.0,
    "isSponsor": false
  }
]